LICENSE.md
MANIFEST.in
README.md
requirements.txt
setup.py
django_rigger.egg-info/PKG-INFO
django_rigger.egg-info/SOURCES.txt
django_rigger.egg-info/dependency_links.txt
django_rigger.egg-info/requires.txt
django_rigger.egg-info/top_level.txt
rigger/__init__.py
rigger/apps.py
rigger/mixin.py
rigger/models.py
rigger/regexes.py
rigger/request.py
rigger/response.py
rigger/settings.py
rigger/validators.py
rigger/viewsets.py
rigger/utils/__init__.py
rigger/utils/return_meta.py
rigger/utils/utils.py