Metadata-Version: 2.1
Name: django-rigger
Version: 1.0.3
Summary: rigger is a django toolset that provides a daily common tools
Home-page: https://github.com/MangoodLuck/django-rigger.git
Author: Xiao Man
Author-email: cloudbye@163.com
Maintainer: Xiao Man
Maintainer-email: cloudbye@163.com
License: MIT
Platform: linux
Requires-Python: >=3.5
